windyquery/__init__.py
windyquery/builder.py
windyquery/connection.py
windyquery/ctx.py
windyquery/db.py
windyquery/exceptions.py
windyquery/listener.py
windyquery/model.py
windyquery/parser.py
windyquery/schema.py
windyquery/utils.py
windyquery/builder/__init__.py
windyquery/builder/_crud_base.py
windyquery/builder/_schema_base.py
windyquery/builder/alter.py
windyquery/builder/create.py
windyquery/builder/delete.py
windyquery/builder/drop.py
windyquery/builder/insert.py
windyquery/builder/raw.py
windyquery/builder/rrule.py
windyquery/builder/select.py
windyquery/builder/update.py
windyquery/builder/with_values.py
windyquery/collector/__init__.py
windyquery/collector/_base.py
windyquery/collector/alter.py
windyquery/collector/create.py
windyquery/collector/delete.py
windyquery/collector/drop.py
windyquery/collector/from_table.py
windyquery/collector/group_by.py
windyquery/collector/insert.py
windyquery/collector/join.py
windyquery/collector/limit.py
windyquery/collector/offset.py
windyquery/collector/on_conflict.py
windyquery/collector/order_by.py
windyquery/collector/raw.py
windyquery/collector/returning.py
windyquery/collector/rrule.py
windyquery/collector/schema.py
windyquery/collector/select.py
windyquery/collector/table.py
windyquery/collector/update.py
windyquery/collector/where.py
windyquery/collector/with_values.py
windyquery/combiner/__init__.py
windyquery/combiner/_base.py
windyquery/combiner/alter_stmt.py
windyquery/combiner/create_stmt.py
windyquery/combiner/delete_stmt.py
windyquery/combiner/drop_stmt.py
windyquery/combiner/insert_stmt.py
windyquery/combiner/parsetab.py
windyquery/combiner/raw_stmt.py
windyquery/combiner/select_stmt.py
windyquery/combiner/update_stmt.py
windyquery/provider/__init__.py
windyquery/provider/_base.py
windyquery/provider/biop.py
windyquery/provider/fieldlist.py
windyquery/provider/glue.py
windyquery/provider/param.py
windyquery/provider/parentheses.py
windyquery/provider/record.py
windyquery/scripts/__init__.py
windyquery-0.0.33.dist-info/LICENSE
windyquery-0.0.33.dist-info/METADATA
windyquery-0.0.33.dist-info/WHEEL
windyquery-0.0.33.dist-info/entry_points.txt
windyquery-0.0.33.dist-info/top_level.txt
windyquery-0.0.33.dist-info/RECORD
