Metadata-Version: 2.1
Name: windyquery
Version: 0.0.33
Summary: A non-blocking PostgreSQL query builder using Asyncio
Home-page: https://github.com/bluerelay/windyquery
Author: windymile.it
Author-email: windymile.it@gmail.com
License: UNKNOWN
Platform: UNKNOWN
Classifier: Programming Language :: Python :: 3.6
Classifier: License :: OSI Approved :: MIT License
Classifier: Operating System :: OS Independent
Requires-Dist: asyncpg (==0.23.0)
Requires-Dist: ply (==3.11)
Requires-Dist: python-dateutil (==2.8.1)
Requires-Dist: fire (==0.4.0)
